midi2audio.py
midi2audio-0.1.1.data/scripts/install_fluidsynth_with_soundfonts_osx.sh
midi2audio-0.1.1.dist-info/DESCRIPTION.rst
midi2audio-0.1.1.dist-info/METADATA
midi2audio-0.1.1.dist-info/RECORD
midi2audio-0.1.1.dist-info/WHEEL
midi2audio-0.1.1.dist-info/entry_points.txt
midi2audio-0.1.1.dist-info/metadata.json
midi2audio-0.1.1.dist-info/top_level.txt
