Metadata-Version: 1.1
Name: midi2audio
Version: 0.1.1
Summary: Easy to use MIDI to audio or playback via FluidSynth
Home-page: https://github.com/bzamecnik/midi2audio
Author: Bohumir Zamecnik
Author-email: bohumir.zamecnik@gmail.com
License: MIT
Platform: UNKNOWN
Classifier: Development Status :: 3 - Alpha
Classifier: Intended Audience :: Developers
Classifier: Intended Audience :: Science/Research
Classifier: Topic :: Multimedia :: Sound/Audio :: Analysis
Classifier: License :: OSI Approved :: MIT License
Classifier: Programming Language :: Python :: 3
Classifier: Operating System :: POSIX :: Linux
Classifier: Operating System :: MacOS :: MacOS X
